{
  "total_prs": 1397,
  "matched_prs": 1397,
  "unmatched_prs": 0,
  "pr_with_patch": 1395,
  "pr_patch_coverage": 99.86,
  "total_files": 31817,
  "files_with_patch": 30778,
  "file_patch_coverage": 96.73,
  "total_added_lines": 2249967,
  "extension_distribution": {
    ".go": 8344,
    ".js": 4923,
    ".md": 4810,
    ".ts": 3049,
    ".json": 2229,
    ".py": 2035,
    ".yaml": 1412,
    "": 1108,
    ".sh": 504,
    ".rs": 443,
    ".pb": 415,
    ".yml": 345,
    ".tsx": 301,
    ".sum": 242,
    ".mod": 174,
    ".rst": 107,
    ".sqlite": 97,
    ".txt": 95,
    ".css": 95,
    ".proto": 94,
    ".lock": 81,
    ".toml": 65,
    ".key": 62,
    ".mts": 60,
    ".svg": 56,
    ".png": 55,
    ".ipynb": 46,
    ".pyx": 44,
    ".jsx": 36,
    ".ico": 33
  }
}